qec_lego_bench/__init__.py
qec_lego_bench/__main__.py
qec_lego_bench/skeleton.py
qec_lego_bench/stats.py
qec_lego_bench/cli/__init__.py
qec_lego_bench/cli/codes.py
qec_lego_bench/cli/decoders.py
qec_lego_bench/cli/logical_error_rate.py
qec_lego_bench/cli/noises.py
qec_lego_bench/cli/util.py
qec_lego_bench/codes/__init__.py
qec_lego_bench/codes/circuit_code.py
qec_lego_bench/codes/code.py
qec_lego_bench/codes/noisy_codes/__init__.py
qec_lego_bench/codes/noisy_codes/noisy_color_code.py
qec_lego_bench/codes/noisy_codes/noisy_repetition_code.py
qec_lego_bench/codes/noisy_codes/noisy_rotated_surface_code.py
qec_lego_bench/codes/noisy_codes/noisy_unrotated_surface_code.py
qec_lego_bench/codes/stabilizer_codes/__init__.py
qec_lego_bench/codes/stabilizer_codes/stabilizer_code.py
qec_lego_bench/codes/stabilizer_codes/css_codes/__init__.py
qec_lego_bench/codes/stabilizer_codes/css_codes/bb_code.py
qec_lego_bench/codes/stabilizer_codes/css_codes/css_code.py
qec_lego_bench/codes/stabilizer_codes/css_codes/rotated_surface_code.py
qec_lego_bench/decoders/__init__.py
qec_lego_bench/decoders/bplsd.py
qec_lego_bench/decoders/bposd.py
qec_lego_bench/decoders/bpuf.py
qec_lego_bench/decoders/chromobius.py
qec_lego_bench/decoders/decoder.py
qec_lego_bench/noises/__init__.py
qec_lego_bench/noises/depolarize_noise.py
qec_lego_bench/noises/flip_noise.py
qec_lego_bench/noises/no_noise.py
qec_lego_bench/noises/noise.py
qec_lego_bench-0.0.3.dist-info/LICENSE.txt
qec_lego_bench-0.0.3.dist-info/METADATA
qec_lego_bench-0.0.3.dist-info/WHEEL
qec_lego_bench-0.0.3.dist-info/entry_points.txt
qec_lego_bench-0.0.3.dist-info/top_level.txt
qec_lego_bench-0.0.3.dist-info/RECORD
