Metadata-Version: 2.2
Name: qec_lego_bench
Version: 0.0.3
Summary: Add a short description here!
Home-page: https://github.com/yuewuo/qec-lego-bench/
Author: Yue Wu
Author-email: yue.wu@yale.edu
License: MIT
Project-URL: Documentation, https://qec-lego-bench.readthedocs.io
Platform: any
Classifier: Development Status :: 4 - Beta
Classifier: Programming Language :: Python
Requires-Python: >=3.9
License-File: LICENSE.txt
Requires-Dist: importlib-metadata; python_version < "3.8"
Requires-Dist: stim<2.0,>=1.0
Requires-Dist: sinter<2.0,>=1.0
Requires-Dist: mwpf<0.3,>=0.2.5
Requires-Dist: mwpf-rational<0.3,>=0.2.5
Requires-Dist: numpy
Requires-Dist: galois
Requires-Dist: arguably<2.0,>=1.0
Requires-Dist: ldpc>=2.2.8
Requires-Dist: chromobius
Requires-Dist: uncertainties
Requires-Dist: tqdm
Provides-Extra: dev
Requires-Dist: mypy; extra == "dev"
Requires-Dist: pylint; extra == "dev"
Provides-Extra: testing
Requires-Dist: setuptools; extra == "testing"
Requires-Dist: pytest; extra == "testing"
Requires-Dist: pytest-cov; extra == "testing"
